nfuzz/ExpectError.py
nfuzz/Fuzzer.py
nfuzz/GrammarFuzzer.py
nfuzz/Grammars.py
nfuzz/MutationFuzzer.py
nfuzz/WebFuzzer.py
nfuzz/__init__.py
nfuzz/nfuzz_utils/__init__.py
nfuzz-0.0.5.dist-info/LICENSE
nfuzz-0.0.5.dist-info/METADATA
nfuzz-0.0.5.dist-info/WHEEL
nfuzz-0.0.5.dist-info/top_level.txt
nfuzz-0.0.5.dist-info/RECORD
