Metadata-Version: 2.1
Name: nfuzz
Version: 0.0.5
Summary: A useful tool for fuzz job.
Home-page: https://github.com/alexqiaodan/nfuzz
Author: alexqiaodan
Author-email: sunqiao@corp.netease.com
License: UNKNOWN
Platform: UNKNOWN
Classifier: Programming Language :: Python :: 3
Classifier: License :: OSI Approved :: MIT License
Classifier: Operating System :: OS Independent
Requires-Dist: requests
Requires-Dist: iPython
Requires-Dist: nbformat
Requires-Dist: graphviz
